sdk/__init__.py
sdk/requirements.txt
sdk/adapter/__init__.py
sdk/adapter/qdrant/__init__.py
sdk/adapter/qdrant/embeddings.py
sdk/adapter/qdrant/requiremetns.txt
sdk/adapter/qdrant/vector_db_adapter.py
sdk/adapter/qdrant/__pycache__/__init__.cpython-311.pyc
sdk/adapter/qdrant/__pycache__/vector_db_adapter.cpython-311.pyc
sdk/airembr/__init__.py
sdk/airembr/client.py
sdk/airembr/__pycache__/client.cpython-311.pyc
sdk/airembr/model/__init__.py
sdk/airembr/model/entity.py
sdk/airembr/model/fact.py
sdk/airembr/model/instance.py
sdk/airembr/model/instance_link.py
sdk/airembr/model/named_entity.py
sdk/airembr/model/observation.py
sdk/airembr/model/session.py
sdk/airembr/model/time.py
sdk/airembr/model/worker_tags.py
sdk/airembr/model/__pycache__/entity.cpython-311.pyc
sdk/airembr/model/__pycache__/fact.cpython-311.pyc
sdk/airembr/model/__pycache__/instance.cpython-311.pyc
sdk/airembr/model/__pycache__/instance_link.cpython-311.pyc
sdk/airembr/model/__pycache__/named_entity.cpython-311.pyc
sdk/airembr/model/__pycache__/observation.cpython-311.pyc
sdk/airembr/model/__pycache__/session.cpython-311.pyc
sdk/airembr/model/__pycache__/time.cpython-311.pyc
sdk/airembr/model/__pycache__/worker_tags.cpython-311.pyc
sdk/airembr/service/__init__.py
sdk/airembr/service/converters.py
sdk/airembr/service/formaters.py
sdk/airembr/service/sementic.py
sdk/airembr/service/__pycache__/converters.cpython-311.pyc
sdk/airembr/service/__pycache__/formaters.cpython-311.pyc
sdk/airembr/service/__pycache__/sementic.cpython-311.pyc
sdk/airembr/service/api/__init__.py
sdk/airembr/service/api/sync_api.py
sdk/airembr/service/api/__pycache__/sync_api.cpython-311.pyc
sdk/airembr/service/time/__init__.py
sdk/airembr/service/time/time.py
sdk/airembr/service/time/__pycache__/time.cpython-311.pyc
sdk/airembr/service/uuid/__init__.py
sdk/airembr/service/uuid/uuid_generator.py
sdk/airembr/service/uuid/__pycache__/uuid_generator.cpython-311.pyc
sdk/airembr/transport/__init__.py
airembr_sdk-0.0.1.dist-info/METADATA
airembr_sdk-0.0.1.dist-info/WHEEL
airembr_sdk-0.0.1.dist-info/top_level.txt
airembr_sdk-0.0.1.dist-info/RECORD
