Metadata-Version: 2.4
Name: airembr-sdk
Version: 0.0.1
Summary: Airembr SDK
Author: Risto Kowaczewski
Keywords: airembr,sdk
Classifier: Programming Language :: Python :: 3
Classifier: License :: OSI Approved :: MIT License
Classifier: Operating System :: OS Independent
Requires-Python: >=3.10
Requires-Dist: pydantic
Requires-Dist: jinja2
Requires-Dist: durable-dot-dict>=0.0.20
Requires-Dist: python-dateutil
Requires-Dist: requests
Requires-Dist: pulsar-client==3.5.0
Requires-Dist: kafka-python==2.1.5
Requires-Dist: aiokafka==0.12.0
Dynamic: author
Dynamic: classifier
Dynamic: description
Dynamic: description-content-type
Dynamic: keywords
Dynamic: requires-dist
Dynamic: requires-python
Dynamic: summary
